{"nodes": [{"id": "backend_vendor_codeigniter4_framework_system_commands_database_seed_php", "label": "Seed.php", "file_type": "code", "source_file": "backend\\vendor\\codeigniter4\\framework\\system\\Commands\\Database\\Seed.php", "source_location": "L1"}, {"id": "seed_seed", "label": "Seed", "file_type": "code", "source_file": "backend\\vendor\\codeigniter4\\framework\\system\\Commands\\Database\\Seed.php", "source_location": "L26"}, {"id": "seed_seed_run", "label": ".run()", "file_type": "code", "source_file": "backend\\vendor\\codeigniter4\\framework\\system\\Commands\\Database\\Seed.php", "source_location": "L69"}], "edges": [{"source": "backend_vendor_codeigniter4_framework_system_commands_database_seed_php", "target": "basecommand", "relation": "imports", "confidence": "EXTRACTED", "source_file": "backend\\vendor\\codeigniter4\\framework\\system\\Commands\\Database\\Seed.php", "source_location": "L16", "weight": 1.0}, {"source": "backend_vendor_codeigniter4_framework_system_commands_database_seed_php", "target": "cli", "relation": "imports", "confidence": "EXTRACTED", "source_file": "backend\\vendor\\codeigniter4\\framework\\system\\Commands\\Database\\Seed.php", "source_location": "L17", "weight": 1.0}, {"source": "backend_vendor_codeigniter4_framework_system_commands_database_seed_php", "target": "seeder", "relation": "imports", "confidence": "EXTRACTED", "source_file": "backend\\vendor\\codeigniter4\\framework\\system\\Commands\\Database\\Seed.php", "source_location": "L18", "weight": 1.0}, {"source": "backend_vendor_codeigniter4_framework_system_commands_database_seed_php", "target": "database", "relation": "imports", "confidence": "EXTRACTED", "source_file": "backend\\vendor\\codeigniter4\\framework\\system\\Commands\\Database\\Seed.php", "source_location": "L19", "weight": 1.0}, {"source": "backend_vendor_codeigniter4_framework_system_commands_database_seed_php", "target": "throwable", "relation": "imports", "confidence": "EXTRACTED", "source_file": "backend\\vendor\\codeigniter4\\framework\\system\\Commands\\Database\\Seed.php", "source_location": "L20", "weight": 1.0}, {"source": "backend_vendor_codeigniter4_framework_system_commands_database_seed_php", "target": "seed_seed", "relation": "contains", "confidence": "EXTRACTED", "source_file": "backend\\vendor\\codeigniter4\\framework\\system\\Commands\\Database\\Seed.php", "source_location": "L26", "weight": 1.0}, {"source": "seed_seed", "target": "seed_seed_run", "relation": "method", "confidence": "EXTRACTED", "source_file": "backend\\vendor\\codeigniter4\\framework\\system\\Commands\\Database\\Seed.php", "source_location": "L69", "weight": 1.0}]}