{"nodes": [{"id": "backend_vendor_codeigniter4_framework_system_database_connectioninterface_php", "label": "ConnectionInterface.php", "file_type": "code", "source_file": "backend\\vendor\\codeigniter4\\framework\\system\\Database\\ConnectionInterface.php", "source_location": "L1"}, {"id": "connectioninterface_initialize", "label": "initialize()", "file_type": "code", "source_file": "backend\\vendor\\codeigniter4\\framework\\system\\Database\\ConnectionInterface.php", "source_location": "L30"}, {"id": "connectioninterface_connect", "label": "connect()", "file_type": "code", "source_file": "backend\\vendor\\codeigniter4\\framework\\system\\Database\\ConnectionInterface.php", "source_location": "L37"}, {"id": "connectioninterface_persistentconnect", "label": "persistentConnect()", "file_type": "code", "source_file": "backend\\vendor\\codeigniter4\\framework\\system\\Database\\ConnectionInterface.php", "source_location": "L44"}, {"id": "connectioninterface_reconnect", "label": "reconnect()", "file_type": "code", "source_file": "backend\\vendor\\codeigniter4\\framework\\system\\Database\\ConnectionInterface.php", "source_location": "L52"}, {"id": "connectioninterface_getconnection", "label": "getConnection()", "file_type": "code", "source_file": "backend\\vendor\\codeigniter4\\framework\\system\\Database\\ConnectionInterface.php", "source_location": "L62"}, {"id": "connectioninterface_setdatabase", "label": "setDatabase()", "file_type": "code", "source_file": "backend\\vendor\\codeigniter4\\framework\\system\\Database\\ConnectionInterface.php", "source_location": "L69"}, {"id": "connectioninterface_getdatabase", "label": "getDatabase()", "file_type": "code", "source_file": "backend\\vendor\\codeigniter4\\framework\\system\\Database\\ConnectionInterface.php", "source_location": "L74"}, {"id": "connectioninterface_error", "label": "error()", "file_type": "code", "source_file": "backend\\vendor\\codeigniter4\\framework\\system\\Database\\ConnectionInterface.php", "source_location": "L83"}, {"id": "connectioninterface_getplatform", "label": "getPlatform()", "file_type": "code", "source_file": "backend\\vendor\\codeigniter4\\framework\\system\\Database\\ConnectionInterface.php", "source_location": "L88"}, {"id": "connectioninterface_getversion", "label": "getVersion()", "file_type": "code", "source_file": "backend\\vendor\\codeigniter4\\framework\\system\\Database\\ConnectionInterface.php", "source_location": "L93"}, {"id": "connectioninterface_query", "label": "query()", "file_type": "code", "source_file": "backend\\vendor\\codeigniter4\\framework\\system\\Database\\ConnectionInterface.php", "source_location": "L107"}, {"id": "connectioninterface_simplequery", "label": "simpleQuery()", "file_type": "code", "source_file": "backend\\vendor\\codeigniter4\\framework\\system\\Database\\ConnectionInterface.php", "source_location": "L116"}, {"id": "connectioninterface_table", "label": "table()", "file_type": "code", "source_file": "backend\\vendor\\codeigniter4\\framework\\system\\Database\\ConnectionInterface.php", "source_location": "L125"}, {"id": "connectioninterface_getlastquery", "label": "getLastQuery()", "file_type": "code", "source_file": "backend\\vendor\\codeigniter4\\framework\\system\\Database\\ConnectionInterface.php", "source_location": "L132"}, {"id": "connectioninterface_escape", "label": "escape()", "file_type": "code", "source_file": "backend\\vendor\\codeigniter4\\framework\\system\\Database\\ConnectionInterface.php", "source_location": "L144"}, {"id": "connectioninterface_callfunction", "label": "callFunction()", "file_type": "code", "source_file": "backend\\vendor\\codeigniter4\\framework\\system\\Database\\ConnectionInterface.php", "source_location": "L154"}, {"id": "connectioninterface_iswritetype", "label": "isWriteType()", "file_type": "code", "source_file": "backend\\vendor\\codeigniter4\\framework\\system\\Database\\ConnectionInterface.php", "source_location": "L161"}], "edges": [{"source": "backend_vendor_codeigniter4_framework_system_database_connectioninterface_php", "target": "connectioninterface_initialize", "relation": "contains", "confidence": "EXTRACTED", "source_file": "backend\\vendor\\codeigniter4\\framework\\system\\Database\\ConnectionInterface.php", "source_location": "L30", "weight": 1.0}, {"source": "backend_vendor_codeigniter4_framework_system_database_connectioninterface_php", "target": "connectioninterface_connect", "relation": "contains", "confidence": "EXTRACTED", "source_file": "backend\\vendor\\codeigniter4\\framework\\system\\Database\\ConnectionInterface.php", "source_location": "L37", "weight": 1.0}, {"source": "backend_vendor_codeigniter4_framework_system_database_connectioninterface_php", "target": "connectioninterface_persistentconnect", "relation": "contains", "confidence": "EXTRACTED", "source_file": "backend\\vendor\\codeigniter4\\framework\\system\\Database\\ConnectionInterface.php", "source_location": "L44", "weight": 1.0}, {"source": "backend_vendor_codeigniter4_framework_system_database_connectioninterface_php", "target": "connectioninterface_reconnect", "relation": "contains", "confidence": "EXTRACTED", "source_file": "backend\\vendor\\codeigniter4\\framework\\system\\Database\\ConnectionInterface.php", "source_location": "L52", "weight": 1.0}, {"source": "backend_vendor_codeigniter4_framework_system_database_connectioninterface_php", "target": "connectioninterface_getconnection", "relation": "contains", "confidence": "EXTRACTED", "source_file": "backend\\vendor\\codeigniter4\\framework\\system\\Database\\ConnectionInterface.php", "source_location": "L62", "weight": 1.0}, {"source": "backend_vendor_codeigniter4_framework_system_database_connectioninterface_php", "target": "connectioninterface_setdatabase", "relation": "contains", "confidence": "EXTRACTED", "source_file": "backend\\vendor\\codeigniter4\\framework\\system\\Database\\ConnectionInterface.php", "source_location": "L69", "weight": 1.0}, {"source": "backend_vendor_codeigniter4_framework_system_database_connectioninterface_php", "target": "connectioninterface_getdatabase", "relation": "contains", "confidence": "EXTRACTED", "source_file": "backend\\vendor\\codeigniter4\\framework\\system\\Database\\ConnectionInterface.php", "source_location": "L74", "weight": 1.0}, {"source": "backend_vendor_codeigniter4_framework_system_database_connectioninterface_php", "target": "connectioninterface_error", "relation": "contains", "confidence": "EXTRACTED", "source_file": "backend\\vendor\\codeigniter4\\framework\\system\\Database\\ConnectionInterface.php", "source_location": "L83", "weight": 1.0}, {"source": "backend_vendor_codeigniter4_framework_system_database_connectioninterface_php", "target": "connectioninterface_getplatform", "relation": "contains", "confidence": "EXTRACTED", "source_file": "backend\\vendor\\codeigniter4\\framework\\system\\Database\\ConnectionInterface.php", "source_location": "L88", "weight": 1.0}, {"source": "backend_vendor_codeigniter4_framework_system_database_connectioninterface_php", "target": "connectioninterface_getversion", "relation": "contains", "confidence": "EXTRACTED", "source_file": "backend\\vendor\\codeigniter4\\framework\\system\\Database\\ConnectionInterface.php", "source_location": "L93", "weight": 1.0}, {"source": "backend_vendor_codeigniter4_framework_system_database_connectioninterface_php", "target": "connectioninterface_query", "relation": "contains", "confidence": "EXTRACTED", "source_file": "backend\\vendor\\codeigniter4\\framework\\system\\Database\\ConnectionInterface.php", "source_location": "L107", "weight": 1.0}, {"source": "backend_vendor_codeigniter4_framework_system_database_connectioninterface_php", "target": "connectioninterface_simplequery", "relation": "contains", "confidence": "EXTRACTED", "source_file": "backend\\vendor\\codeigniter4\\framework\\system\\Database\\ConnectionInterface.php", "source_location": "L116", "weight": 1.0}, {"source": "backend_vendor_codeigniter4_framework_system_database_connectioninterface_php", "target": "connectioninterface_table", "relation": "contains", "confidence": "EXTRACTED", "source_file": "backend\\vendor\\codeigniter4\\framework\\system\\Database\\ConnectionInterface.php", "source_location": "L125", "weight": 1.0}, {"source": "backend_vendor_codeigniter4_framework_system_database_connectioninterface_php", "target": "connectioninterface_getlastquery", "relation": "contains", "confidence": "EXTRACTED", "source_file": "backend\\vendor\\codeigniter4\\framework\\system\\Database\\ConnectionInterface.php", "source_location": "L132", "weight": 1.0}, {"source": "backend_vendor_codeigniter4_framework_system_database_connectioninterface_php", "target": "connectioninterface_escape", "relation": "contains", "confidence": "EXTRACTED", "source_file": "backend\\vendor\\codeigniter4\\framework\\system\\Database\\ConnectionInterface.php", "source_location": "L144", "weight": 1.0}, {"source": "backend_vendor_codeigniter4_framework_system_database_connectioninterface_php", "target": "connectioninterface_callfunction", "relation": "contains", "confidence": "EXTRACTED", "source_file": "backend\\vendor\\codeigniter4\\framework\\system\\Database\\ConnectionInterface.php", "source_location": "L154", "weight": 1.0}, {"source": "backend_vendor_codeigniter4_framework_system_database_connectioninterface_php", "target": "connectioninterface_iswritetype", "relation": "contains", "confidence": "EXTRACTED", "source_file": "backend\\vendor\\codeigniter4\\framework\\system\\Database\\ConnectionInterface.php", "source_location": "L161", "weight": 1.0}]}