{"nodes": [{"id": "d_company_work_company_projects_attendance_software_employee_app_services_salaryservice_php", "label": "SalaryService.php", "file_type": "code", "source_file": "D:\\Company Work\\Company projects\\Attendance software\\employee\\app\\Services\\SalaryService.php", "source_location": "L1"}, {"id": "salaryservice_salaryservice", "label": "SalaryService", "file_type": "code", "source_file": "D:\\Company Work\\Company projects\\Attendance software\\employee\\app\\Services\\SalaryService.php", "source_location": "L12"}, {"id": "salaryservice_salaryservice_construct", "label": ".__construct()", "file_type": "code", "source_file": "D:\\Company Work\\Company projects\\Attendance software\\employee\\app\\Services\\SalaryService.php", "source_location": "L21"}, {"id": "salaryservice_salaryservice_calculateemployeesalary", "label": ".calculateEmployeeSalary()", "file_type": "code", "source_file": "D:\\Company Work\\Company projects\\Attendance software\\employee\\app\\Services\\SalaryService.php", "source_location": "L34"}, {"id": "salaryservice_salaryservice_computesalary", "label": ".computeSalary()", "file_type": "code", "source_file": "D:\\Company Work\\Company projects\\Attendance software\\employee\\app\\Services\\SalaryService.php", "source_location": "L110"}], "edges": [{"source": "d_company_work_company_projects_attendance_software_employee_app_services_salaryservice_php", "target": "attendancedailymodel", "relation": "imports", "confidence": "EXTRACTED", "source_file": "D:\\Company Work\\Company projects\\Attendance software\\employee\\app\\Services\\SalaryService.php", "source_location": "L5", "weight": 1.0}, {"source": "d_company_work_company_projects_attendance_software_employee_app_services_salaryservice_php", "target": "employeemodel", "relation": "imports", "confidence": "EXTRACTED", "source_file": "D:\\Company Work\\Company projects\\Attendance software\\employee\\app\\Services\\SalaryService.php", "source_location": "L6", "weight": 1.0}, {"source": "d_company_work_company_projects_attendance_software_employee_app_services_salaryservice_php", "target": "employeesalarycomponentmodel", "relation": "imports", "confidence": "EXTRACTED", "source_file": "D:\\Company Work\\Company projects\\Attendance software\\employee\\app\\Services\\SalaryService.php", "source_location": "L7", "weight": 1.0}, {"source": "d_company_work_company_projects_attendance_software_employee_app_services_salaryservice_php", "target": "salaryservice_salaryservice", "relation": "contains", "confidence": "EXTRACTED", "source_file": "D:\\Company Work\\Company projects\\Attendance software\\employee\\app\\Services\\SalaryService.php", "source_location": "L12", "weight": 1.0}, {"source": "salaryservice_salaryservice", "target": "salaryservice_salaryservice_construct", "relation": "method", "confidence": "EXTRACTED", "source_file": "D:\\Company Work\\Company projects\\Attendance software\\employee\\app\\Services\\SalaryService.php", "source_location": "L21", "weight": 1.0}, {"source": "salaryservice_salaryservice", "target": "salaryservice_salaryservice_calculateemployeesalary", "relation": "method", "confidence": "EXTRACTED", "source_file": "D:\\Company Work\\Company projects\\Attendance software\\employee\\app\\Services\\SalaryService.php", "source_location": "L34", "weight": 1.0}, {"source": "salaryservice_salaryservice", "target": "salaryservice_salaryservice_computesalary", "relation": "method", "confidence": "EXTRACTED", "source_file": "D:\\Company Work\\Company projects\\Attendance software\\employee\\app\\Services\\SalaryService.php", "source_location": "L110", "weight": 1.0}, {"source": "salaryservice_salaryservice_calculateemployeesalary", "target": "salaryservice_salaryservice_computesalary", "relation": "calls", "confidence": "EXTRACTED", "source_file": "D:\\Company Work\\Company projects\\Attendance software\\employee\\app\\Services\\SalaryService.php", "source_location": "L104", "weight": 1.0}]}