{"nodes": [{"id": "backend_vendor_phpunit_phpunit_src_runner_filter_excludegroupfilteriterator_php", "label": "ExcludeGroupFilterIterator.php", "file_type": "code", "source_file": "backend\\vendor\\phpunit\\phpunit\\src\\Runner\\Filter\\ExcludeGroupFilterIterator.php", "source_location": "L1"}, {"id": "excludegroupfilteriterator_excludegroupfilteriterator", "label": "ExcludeGroupFilterIterator", "file_type": "code", "source_file": "backend\\vendor\\phpunit\\phpunit\\src\\Runner\\Filter\\ExcludeGroupFilterIterator.php", "source_location": "L19"}, {"id": "excludegroupfilteriterator_excludegroupfilteriterator_doaccept", "label": ".doAccept()", "file_type": "code", "source_file": "backend\\vendor\\phpunit\\phpunit\\src\\Runner\\Filter\\ExcludeGroupFilterIterator.php", "source_location": "L21"}], "edges": [{"source": "backend_vendor_phpunit_phpunit_src_runner_filter_excludegroupfilteriterator_php", "target": "in_array", "relation": "imports", "confidence": "EXTRACTED", "source_file": "backend\\vendor\\phpunit\\phpunit\\src\\Runner\\Filter\\ExcludeGroupFilterIterator.php", "source_location": "L12", "weight": 1.0}, {"source": "backend_vendor_phpunit_phpunit_src_runner_filter_excludegroupfilteriterator_php", "target": "excludegroupfilteriterator_excludegroupfilteriterator", "relation": "contains", "confidence": "EXTRACTED", "source_file": "backend\\vendor\\phpunit\\phpunit\\src\\Runner\\Filter\\ExcludeGroupFilterIterator.php", "source_location": "L19", "weight": 1.0}, {"source": "excludegroupfilteriterator_excludegroupfilteriterator", "target": "excludegroupfilteriterator_excludegroupfilteriterator_doaccept", "relation": "method", "confidence": "EXTRACTED", "source_file": "backend\\vendor\\phpunit\\phpunit\\src\\Runner\\Filter\\ExcludeGroupFilterIterator.php", "source_location": "L21", "weight": 1.0}]}